myepg_georgia/__init__.py
myepg_georgia-1.0.3.dist-info/WHEEL
myepg_georgia-1.0.3.dist-info/METADATA
myepg_georgia-1.0.3.dist-info/RECORD
