Metadata-Version: 2.1
Name: myepg-georgia
Version: 1.0.3
Summary: 
Author: Giorgi Kotchlamazashvili
Author-email: georgedot@gmail.com
Requires-Python: >3.8
Classifier: Programming Language :: Python :: 3
Classifier: Programming Language :: Python :: 3.9
Classifier: Programming Language :: Python :: 3.10
Classifier: Programming Language :: Python :: 3.11
Requires-Dist: pyjwt (==2.5.0)
Requires-Dist: requests (==2.28.1)
